mydebug/__init__.py
mydebug/debugMode.py
mydebug-0.1.1.dist-info/METADATA
mydebug-0.1.1.dist-info/WHEEL
mydebug-0.1.1.dist-info/top_level.txt
mydebug-0.1.1.dist-info/RECORD
