Metadata-Version: 2.1
Name: mydebug
Version: 0.1.1
Summary: A simple debugging tool for Python
Home-page: UNKNOWN
Author: p4ylex
License: UNKNOWN
Platform: UNKNOWN
